README.md
setup.cfg
setup.py
examples/__init__.py
sox_chords/__init__.py
sox_chords/exceptions.py
sox_chords/generator.py
sox_chords/values.py
sox_chords.egg-info/PKG-INFO
sox_chords.egg-info/SOURCES.txt
sox_chords.egg-info/dependency_links.txt
sox_chords.egg-info/entry_points.txt
sox_chords.egg-info/namespace_packages.txt
sox_chords.egg-info/requires.txt
sox_chords.egg-info/top_level.txt
sox_chords/music/__init__.py
sox_chords/music/base.py
sox_chords/music/chord.py
sox_chords/music/dataset.py
sox_chords/music/mapping.py
sox_chords/music/scale.py
sox_chords/music/song.py
sox_chords/music/spezial_chords.py
sox_chords/music/utils.py
sox_chords/music/chords/__init__.py
sox_chords/music/chords/seventh.py
sox_chords/music/chords/sus.py
sox_chords/music/chords/triad.py
sox_chords/util/__init__.py
sox_chords/util/generators.py
sox_chords/util/image.py
sox_chords/util/logger.py
sox_chords/util/processors.py
sox_chords/util/sox.py
sox_chords/util/utils.py
sox_chords/util/visualize.py