Metadata-Version: 2.1
Name: sox-chords
Version: 0.1.4
Summary: Generating Guitar Chords using sox
Home-page: https://github.com/baudcode/sox-chords
Author: Malte Koch
Author-email: malte-koch@gmx.net
Maintainer: Malte Koch
Maintainer-email: malte-koch@gmx.net
License: MIT
Download-URL: https://github.com/baudcode/sox-chords/archive/v0.1.4.tar.gz
Platform: UNKNOWN
Classifier: Development Status :: 3 - Alpha
Classifier: Intended Audience :: Developers
Classifier: Operating System :: POSIX :: Linux
Classifier: License :: OSI Approved :: MIT License
Classifier: Programming Language :: Python :: 3
Classifier: Programming Language :: Python :: 2
Classifier: Programming Language :: Python :: 2.7
Classifier: Programming Language :: Python :: 3.4
Classifier: Programming Language :: Python :: 3.5
Classifier: Programming Language :: Python :: 3.6
